{"name":"adform.net","entries":[{"date":"2020.02","prevalence":0.0739,"sites":3196,"fingerprinting":3,"cookies":0.0641},{"date":"2020.03","prevalence":0.0971,"sites":4773,"fingerprinting":3,"cookies":0.0886},{"date":"2020.04","prevalence":0.0806,"sites":3763,"fingerprinting":3,"cookies":0.071},{"date":"2020.05","prevalence":0.0719,"sites":5043,"fingerprinting":3,"cookies":0.0631},{"date":"2020.06","prevalence":0.0837,"sites":6115,"fingerprinting":3,"cookies":0.0763},{"date":"2020.07","prevalence":0.101,"sites":7261,"fingerprinting":3,"cookies":0.0935}]}