{"name":"clickcertain.com","entries":[{"date":"2020.02","prevalence":0.00176,"sites":76,"fingerprinting":0,"cookies":0.00176},{"date":"2020.03","prevalence":0.00321,"sites":158,"fingerprinting":0,"cookies":0.00321},{"date":"2020.04","prevalence":0.00326,"sites":152,"fingerprinting":0,"cookies":0.00321},{"date":"2020.05","prevalence":0.00309,"sites":217,"fingerprinting":0,"cookies":0.00305},{"date":"2020.06","prevalence":0.0191,"sites":1396,"fingerprinting":0,"cookies":0.0191},{"date":"2020.07","prevalence":0.00874,"sites":631,"fingerprinting":0,"cookies":0.00872}]}