{"name":"kxcdn.com","entries":[{"date":"2020.02","prevalence":0.00442,"sites":191,"fingerprinting":1,"cookies":0.00123},{"date":"2020.03","prevalence":0.00419,"sites":206,"fingerprinting":1,"cookies":0.000915},{"date":"2020.04","prevalence":0.00542,"sites":253,"fingerprinting":1,"cookies":0.00118},{"date":"2020.05","prevalence":0.00572,"sites":401,"fingerprinting":1,"cookies":0.00123},{"date":"2020.06","prevalence":0.00813,"sites":594,"fingerprinting":1,"cookies":0.00197},{"date":"2020.07","prevalence":0.00809,"sites":584,"fingerprinting":1,"cookies":0.00198}]}