{"name":"mycdn.co","entries":[{"date":"2020.02","prevalence":0.00067,"sites":29,"fingerprinting":2,"cookies":0.0000694},{"date":"2020.03","prevalence":0.000427,"sites":21,"fingerprinting":2,"cookies":0.0000407},{"date":"2020.04","prevalence":0.000514,"sites":24,"fingerprinting":2,"cookies":0.0000428},{"date":"2020.05","prevalence":0.000399,"sites":28,"fingerprinting":2,"cookies":0.0000143},{"date":"2020.06","prevalence":0.000397,"sites":29,"fingerprinting":2,"cookies":0.000123},{"date":"2020.07","prevalence":0.000346,"sites":25,"fingerprinting":2,"cookies":0.000097}]}