{"name":"redditstatic.com","entries":[{"date":"2020.02","prevalence":0.00351,"sites":152,"fingerprinting":1,"cookies":0.00298},{"date":"2020.03","prevalence":0.00386,"sites":190,"fingerprinting":1,"cookies":0.00315},{"date":"2020.04","prevalence":0.00454,"sites":212,"fingerprinting":1,"cookies":0.00343},{"date":"2020.05","prevalence":0.00449,"sites":315,"fingerprinting":1,"cookies":0.00334},{"date":"2020.06","prevalence":0.00452,"sites":330,"fingerprinting":2,"cookies":0.00383},{"date":"2020.07","prevalence":0.00467,"sites":337,"fingerprinting":1,"cookies":0.00384}]}