{"filename":"ID5 Technology Ltd.json","name":"ID5 Technology Ltd","entries":[{"date":"2020.02","prevalence":{"tracking":0.00754,"nonTracking":0.000416,"total":0.00796},"properties":1},{"date":"2020.03","prevalence":{"tracking":0.0213,"nonTracking":0.000203,"total":0.0215},"properties":1},{"date":"2020.04","prevalence":{"tracking":0.0201,"nonTracking":0.00231,"total":0.0224},"properties":1},{"date":"2020.05","prevalence":{"tracking":0.018,"nonTracking":0.00281,"total":0.0208},"properties":1},{"date":"2020.06","prevalence":{"tracking":0.0206,"nonTracking":0.00395,"total":0.0246},"properties":1}]}