{"filename":"Signal Digital, Inc..json","name":"Signal Digital, Inc.","entries":[{"date":"2020.02","prevalence":{"tracking":0.00569,"nonTracking":0.00127,"total":0.00696},"properties":3},{"date":"2020.03","prevalence":{"tracking":0.00565,"nonTracking":0.000814,"total":0.00646},"properties":3},{"date":"2020.04","prevalence":{"tracking":0.00469,"nonTracking":0.00101,"total":0.0057},"properties":3},{"date":"2020.05","prevalence":{"tracking":0.00418,"nonTracking":0.00113,"total":0.00531},"properties":3},{"date":"2020.06","prevalence":{"tracking":0.00476,"nonTracking":0.000739,"total":0.0055},"properties":3}]}